<annotation>
  <folder>Jellyfish</folder>
  <filename>094c8a1f90201c14.jpg</filename>
  <path>D:\open_images\OIDv4_ToolKit\OID\Dataset\train\Jellyfish\094c8a1f90201c14.jpg</path>
  <source>
    <database>Unknown</database>
  </source>
  <size>
    <width>768</width>
    <height>1024</height>
    <depth>3</depth>
  </size>
  <segmented>0</segmented>
  <object>
    <name>Jellyfish</name>
    <pose>Unspecified</pose>
    <truncated>0</truncated>
    <difficult>0</difficult>
    <bndbox>
      <xmin>104</xmin>
      <ymin>0</ymin>
      <xmax>658</xmax>
      <ymax>840</ymax>
    </bndbox>
  </object>
</annotation>
