<annotation>
  <folder>Jellyfish</folder>
  <filename>2af71fc332bfaa7c.jpg</filename>
  <path>D:\open_images\OIDv4_ToolKit\OID\Dataset\train\Jellyfish\2af71fc332bfaa7c.jpg</path>
  <source>
    <database>Unknown</database>
  </source>
  <size>
    <width>600</width>
    <height>600</height>
    <depth>3</depth>
  </size>
  <segmented>0</segmented>
  <object>
    <name>Jellyfish</name>
    <pose>Unspecified</pose>
    <truncated>0</truncated>
    <difficult>0</difficult>
    <bndbox>
      <xmin>94</xmin>
      <ymin>164</ymin>
      <xmax>496</xmax>
      <ymax>402</ymax>
    </bndbox>
  </object>
</annotation>