<annotation>
  <folder>Jellyfish</folder>
  <filename>c8c4f8b2437033bc.jpg</filename>
  <path>D:\open_images\OIDv4_ToolKit\OID\Dataset\train\Jellyfish\c8c4f8b2437033bc.jpg</path>
  <source>
    <database>Unknown</database>
  </source>
  <size>
    <width>600</width>
    <height>600</height>
    <depth>3</depth>
  </size>
  <segmented>0</segmented>
  <object>
    <name>Jellyfish</name>
    <pose>Unspecified</pose>
    <truncated>0</truncated>
    <difficult>0</difficult>
    <bndbox>
      <xmin>38</xmin>
      <ymin>36</ymin>
      <xmax>551</xmax>
      <ymax>599</ymax>
    </bndbox>
  </object>
</annotation>