<annotation>
  <folder>Jellyfish</folder>
  <filename>de6d60cdbd3ec496.jpg</filename>
  <path>D:\open_images\OIDv4_ToolKit\OID\Dataset\train\Jellyfish\de6d60cdbd3ec496.jpg</path>
  <source>
    <database>Unknown</database>
  </source>
  <size>
    <width>600</width>
    <height>600</height>
    <depth>3</depth>
  </size>
  <segmented>0</segmented>
  <object>
    <name>Jellyfish</name>
    <pose>Unspecified</pose>
    <truncated>0</truncated>
    <difficult>0</difficult>
    <bndbox>
      <xmin>38</xmin>
      <ymin>219</ymin>
      <xmax>136</xmax>
      <ymax>340</ymax>
    </bndbox>
  </object>
  <object>
    <name>Jellyfish</name>
    <pose>Unspecified</pose>
    <truncated>0</truncated>
    <difficult>0</difficult>
    <bndbox>
      <xmin>0</xmin>
      <ymin>79</ymin>
      <xmax>56</xmax>
      <ymax>322</ymax>
    </bndbox>
  </object>
  <object>
    <name>Jellyfish</name>
    <pose>Unspecified</pose>
    <truncated>0</truncated>
    <difficult>0</difficult>
    <bndbox>
      <xmin>0</xmin>
      <ymin>0</ymin>
      <xmax>599</xmax>
      <ymax>599</ymax>
    </bndbox>
  </object>
  <object>
    <name>Jellyfish</name>
    <pose>Unspecified</pose>
    <truncated>0</truncated>
    <difficult>0</difficult>
    <bndbox>
      <xmin>54</xmin>
      <ymin>286</ymin>
      <xmax>218</xmax>
      <ymax>512</ymax>
    </bndbox>
  </object>
  <object>
    <name>Jellyfish</name>
    <pose>Unspecified</pose>
    <truncated>0</truncated>
    <difficult>0</difficult>
    <bndbox>
      <xmin>207</xmin>
      <ymin>0</ymin>
      <xmax>599</xmax>
      <ymax>599</ymax>
    </bndbox>
  </object>
  <object>
    <name>Jellyfish</name>
    <pose>Unspecified</pose>
    <truncated>0</truncated>
    <difficult>0</difficult>
    <bndbox>
      <xmin>451</xmin>
      <ymin>102</ymin>
      <xmax>576</xmax>
      <ymax>317</ymax>
    </bndbox>
  </object>
</annotation>